IcedPyGui-0.4.0.dist-info/METADATA
IcedPyGui-0.4.0.dist-info/WHEEL
IcedPyGui-0.4.0.dist-info/licenses/LICENSE
icedpygui/__init__.py
icedpygui/icedpygui.pyi
icedpygui/icedpygui.cpython-311-x86_64-linux-gnu.so
IcedPyGui-0.4.0.dist-info/RECORD
