Metadata-Version: 2.3
Name: IcedPyGui
Version: 0.4.0
Classifier: Programming Language :: Rust
Classifier: Programming Language :: Python :: Implementation :: CPython
Classifier: Programming Language :: Python :: Implementation :: PyPy
License-File: LICENSE
Summary: Python wrapper for Rust Iced
Keywords: iced,iced_aw,gui,rust,python
Author: Charles Ray <icedpygui@gmail.com>
Author-email: Charles Ray <icedpygui@gmail.com>
License: GNU
Requires-Python: >=3.10, <3.13
Project-URL: Homepage, https://github.com/icedpygui/IcedPyGui
Project-URL: Issues, https://github.com/icedpygui/IcedPyGui/issues
